README.md
setup.cfg
setup.py
eis/__init__.py
eis/account/__init__.py
eis/account/api_client.py
eis/account/configuration.py
eis/account/exceptions.py
eis/account/model_utils.py
eis/account/rest.py
eis/account/api/__init__.py
eis/account/api/accounts_api.py
eis/account/api/default_api.py
eis/account/apis/__init__.py
eis/account/model/__init__.py
eis/account/model/account_class.py
eis/account/model/create_account_request_dto.py
eis/account/model/create_account_response_class.py
eis/account/model/get_account_response_class.py
eis/account/model/inline_response200.py
eis/account/model/inline_response503.py
eis/account/model/list_accounts_response_class.py
eis/account/model/policy_class.py
eis/account/model/update_account_request_dto.py
eis/account/model/update_account_response_class.py
eis/account/models/__init__.py
eis_accounts.egg-info/PKG-INFO
eis_accounts.egg-info/SOURCES.txt
eis_accounts.egg-info/dependency_links.txt
eis_accounts.egg-info/requires.txt
eis_accounts.egg-info/top_level.txt
test/test_account_class.py
test/test_accounts_api.py
test/test_create_account_request_dto.py
test/test_create_account_response_class.py
test/test_default_api.py
test/test_get_account_response_class.py
test/test_inline_response200.py
test/test_inline_response503.py
test/test_list_accounts_response_class.py
test/test_policy_class.py
test/test_update_account_request_dto.py
test/test_update_account_response_class.py