Metadata-Version: 2.1
Name: eis-accounts
Version: 1.36.0
Summary: EMIL AccountService
Home-page: UNKNOWN
Author: Contact us
Author-email: kontakt@emil.de
License: UNKNOWN
Keywords: OpenAPI,OpenAPI-Generator,EMIL AccountService
Platform: UNKNOWN
Requires-Python: >=3.6
